{"ancient-creature-nucleus": {"name": "Ancient Creature Nucleus", "locations": [["World 7-S6", 0]]}, "archers-vision": {"name": "Archers Vision", "locations": [["World 7-7", 6], ["World 7-10", 6], ["Normal 4-9", 5]]}, "baby-mouse-insignia": {"name": "Baby Mouse Insignia", "locations": [["World 3-8", 11], ["World 4-S7", 11], ["World 5S-S1", 11], ["Normal 4-4", 10], ["World 7-S4", 8], ["World 7-S5", 8]]}, "black-curse-powder": {"name": "Black Curse Powder", "locations": [["World 10-S2", 0]]}, "blazing-rage": {"name": "Blazing Rage", "locations": [["World 5-5", 11], ["World 5S-3", 11], ["World 10-6", 11], ["Normal 5-5", 10], ["Normal 5-6", 10], ["World 3-S3", 7], ["World 4-S5", 7]]}, "blazing-soul": {"name": "Blazing Soul", "locations": [["World 4-9", 0]]}, "blessing-of-orbis": {"name": "Blessing Of Orbis", "locations": [["World 3S-S1", 11], ["Normal 1-7", 9], ["World 1-7", 9]]}, "blood-flaked-bone": {"name": "Blood Flaked Bone", "locations": [["Normal 1-9", 7], ["Normal 1-10", 7], ["World 1-9", 7], ["World 3-5", 7], ["World 9-S4", 7]]}, "cold-look": {"name": "Cold Look", "locations": [["Normal 8-6", 6], ["World 8-6", 6]]}, "cursed-ashes": {"name": "Cursed Ashes", "locations": [["Normal 3-5", 10], ["World 10-S2", 5], ["World 10-S3", 5], ["World 8-7", 4], ["World 8-8", 4], ["World 8-10", 4]]}, "demon-blood-gem": {"name": "Demon Blood Gem", "locations": [["World 5-6", 0]]}, "dragons-wrath": {"name": "Dragon's Wrath", "locations": [["World 3-S3", 0]]}, "dream-time-circuit": {"name": "Dream Time Circuit", "locations": [["Normal 6-9", 11], ["World 6-9", 11], ["World 7-5", 11], ["World 5S-7", 9], ["World 2-10", 6]]}, "erikion-carapace": {"name": "Erikion Carapace", "locations": [["World 3-4", 11], ["World 5-1", 11], ["Normal 3-S4", 1]]}, "eternal-forest-dust": {"name": "Eternal Forest Dust", "locations": [["Normal 5-3", 6], ["Normal 5-9", 6], ["Normal 5-10", 6], ["World 5-3", 6], ["World 5-8", 6], ["World 5-9", 6], ["World 5-10", 6], ["World 4-S2", 5]]}, "fighter-medal": {"name": "Fighter Medal", "locations": [["World 10-8", 0]]}, "flame-of-soul": {"name": "Flame of Soul", "locations": [["World 9-9", 11], ["Normal 9-7", 10], ["World 4-S11", 4]]}, "fused-nerve": {"name": "Fused Nerve", "locations": [["World 9-8", 0]]}, "horn-of-desire": {"name": "Horn of Desire", "locations": [["World 8-S3", 0]]}, "leather-sheath": {"name": "Leather Sheath", "locations": [["Normal 4-9", 10], ["World 4-8", 4], ["World 7-9", 4], ["World 7-10", 4]]}, "mercenarys-medicine": {"name": "Mercenary's Medicine", "locations": [["World 3-S2", 0]]}, "mysterious-flash": {"name": "Mysterious Flash", "locations": [["Normal 2-1", 7], ["World 2-1", 7], ["World 9-6", 7]]}, "nightmare-mask": {"name": "Nightmare Mask", "locations": [["World 8S-S3", 0], ["World 8S-S4", 0]]}, "order-of-the-shield-insignia": {"name": "Order Of The Shield Insignia", "locations": [["Normal 6-5", 10], ["World 6-2", 6], ["World 6-6", 6]]}, "path-power-loop": {"name": "Path Power Loop", "locations": [["Normal 2-9", 10], ["World 2-7", 7], ["World 2-8", 7], ["World 9-S6", 5]]}, "reingar-student-id": {"name": "Reingar Student ID", "locations": [["World 2-2", 0], ["World 2-9", 0]]}, "ring-of-glory": {"name": "Ring of Glory", "locations": [["Normal 10-3", 38], ["World 9-1", 11]]}, "sharp-spearhead": {"name": "Sharp Spearhead", "locations": [["Normal 4-9", 10], ["World 1-S3", 7], ["World 7-7", 6]]}, "shiny-enchantment": {"name": "Shiny Enchantment", "locations": [["Normal 5-4", 8], ["World 5-4", 8], ["World 1-8", 7]]}, "slime-jelly": {"name": "Slime Jelly", "locations": [["World 9-S1", 11], ["World 3-1", 10], ["Normal 4-1", 7]]}, "small-sun-badge": {"name": "Small Sun Badge", "locations": [["Normal 4-9", 10], ["World 4-8", 4], ["World 9-5", 4], ["World 9-10", 4], ["World 10-7", 4]]}, "special-alarm-loop": {"name": "Special Alarm Loop", "locations": [["Normal 9-4", 12], ["World 2-2", 5]]}, "strange-jelly": {"name": "Strange Jelly", "locations": [["World 10-2", 11], ["Normal 1-10", 9], ["World 4-S11", 6]]}, "the-heart-of-hypocrisy": {"name": "The Heart of Hypocrisy", "locations": [["World 9-10", 0], ["World 10-4", 0]]}, "twisted-fang": {"name": "Twisted Fang", "locations": [["Normal 8-S2", 7], ["World 8-S2", 7]]}, "ultra-fang": {"name": "Ultra Fang", "locations": [["Normal 6-1", 11], ["World 6-1", 11], ["World 5-7", 9]]}}